CHANGES.txt
MANIFEST.in
README.txt
setup.py
slapcache/__init__.py
slapcache/conf.py
slapcache/download.py
slapcache/signature.py
slapcache/upload.py
slapcache.egg-info/PKG-INFO
slapcache.egg-info/SOURCES.txt
slapcache.egg-info/dependency_links.txt
slapcache.egg-info/entry_points.txt
slapcache.egg-info/namespace_packages.txt
slapcache.egg-info/not-zip-safe
slapcache.egg-info/requires.txt
slapcache.egg-info/top_level.txt
slapcache/template/__init__.py
slapcache/template/update.cfg.in
slapcache/test/test_signature.py