Metadata-Version: 1.1
Name: slapcache
Version: 0.1.10
Summary: SlapOS Cache Utils
Home-page: http://www.slapos.org
Author: VIFIB
Author-email: UNKNOWN
License: GPLv3
Keywords: slapos shacache
Platform: UNKNOWN
Classifier: Programming Language :: Python
